odoo/addons/mrp_repair_refurbish/README.rst
odoo/addons/mrp_repair_refurbish/__init__.py
odoo/addons/mrp_repair_refurbish/__manifest__.py
odoo/addons/mrp_repair_refurbish/data/stock_data.xml
odoo/addons/mrp_repair_refurbish/i18n/de.po
odoo/addons/mrp_repair_refurbish/i18n/mrp_repair_refurbish.pot
odoo/addons/mrp_repair_refurbish/models/__init__.py
odoo/addons/mrp_repair_refurbish/models/mrp_repair.py
odoo/addons/mrp_repair_refurbish/models/product_product.py
odoo/addons/mrp_repair_refurbish/models/product_template.py
odoo/addons/mrp_repair_refurbish/readme/CONFIGURE.rst
odoo/addons/mrp_repair_refurbish/readme/CONTRIBUTORS.rst
odoo/addons/mrp_repair_refurbish/readme/CREDITS.rst
odoo/addons/mrp_repair_refurbish/readme/DESCRIPTION.rst
odoo/addons/mrp_repair_refurbish/readme/USAGE.rst
odoo/addons/mrp_repair_refurbish/static/description/icon.png
odoo/addons/mrp_repair_refurbish/static/description/index.html
odoo/addons/mrp_repair_refurbish/tests/__init__.py
odoo/addons/mrp_repair_refurbish/tests/test_mrp_repair_refurbish.py
odoo/addons/mrp_repair_refurbish/views/mrp_repair_view.xml
odoo/addons/mrp_repair_refurbish/views/product_product_view.xml
odoo/addons/mrp_repair_refurbish/views/product_template_view.xml
odoo11_addon_mrp_repair_refurbish-11.0.1.0.1.99.dev5.dist-info/METADATA
odoo11_addon_mrp_repair_refurbish-11.0.1.0.1.99.dev5.dist-info/WHEEL
odoo11_addon_mrp_repair_refurbish-11.0.1.0.1.99.dev5.dist-info/top_level.txt
odoo11_addon_mrp_repair_refurbish-11.0.1.0.1.99.dev5.dist-info/RECORD
